graphutil/__init__.py
graphutil/graphutil.py
graphutil-1.6.2.dist-info/DESCRIPTION.rst
graphutil-1.6.2.dist-info/METADATA
graphutil-1.6.2.dist-info/RECORD
graphutil-1.6.2.dist-info/WHEEL
graphutil-1.6.2.dist-info/metadata.json
graphutil-1.6.2.dist-info/top_level.txt
