Metadata-Version: 2.0
Name: graphutil
Version: 1.6.2
Summary: Graph Processing Library
Home-page: https://github.com/dahvid/graphutil
Author: David Minor
Author-email: dahvid.minor@gmail.com
License: UNKNOWN
Platform: UNKNOWN
Requires-Python: >=2.7
